alphatest/__init__.py
alphatest/alphatest.py
alphatest/util.py
alphatest-0.1.3.dist-info/METADATA
alphatest-0.1.3.dist-info/WHEEL
alphatest-0.1.3.dist-info/licenses/LICENSE
alphatest-0.1.3.dist-info/RECORD
