Metadata-Version: 2.4
Name: alphatest
Version: 0.1.3
Summary: A short description of the alphatest project.
Project-URL: Homepage, https://github.com/utilmon/alphatest
Project-URL: Bug Tracker, https://github.com/utilmon/alphatest/issues
Author-email: utilmon <utilmonn@gmail.com>
License-File: LICENSE
Classifier: License :: OSI Approved :: MIT License
Classifier: Operating System :: OS Independent
Classifier: Programming Language :: Python :: 3
Requires-Python: >=3.8
